{
  "models": {
    "ver10_baseline": {
      "action_score": 0.92,
      "target_score": 0.22,
      "params_score": 0.3013,
      "total": 0.5944
    },
    "ver10_improved": {
      "action_score": 0.99,
      "target_score": 0.8417,
      "params_score": 0.7364,
      "total": 0.8843
    },
    "v11a_ruleplus": {
      "action_score": 0.99,
      "target_score": 0.5817,
      "params_score": 0.6133,
      "total": 0.7953
    },
    "v11d_ensemble": {
      "action_score": 0.99,
      "target_score": 0.8417,
      "params_score": 0.7364,
      "total": 0.8843
    }
  },
  "best_model": "ver10_improved",
  "record_count": 600,
  "variant_distribution": {
    "ver2": 200,
    "ver3": 200,
    "ver4": 200
  },
  "model_output_paths": {
    "ver10_baseline": "/workspace/notebook/ver12_outputs/unknown_predictions_ver10_baseline.json",
    "ver10_improved": "/workspace/notebook/ver12_outputs/unknown_predictions_ver10_improved.json",
    "v11a_ruleplus": "/workspace/notebook/ver12_outputs/unknown_predictions_v11a_ruleplus.json",
    "v11d_ensemble": "/workspace/notebook/ver12_outputs/unknown_predictions_v11d_ensemble.json"
  },
  "note": "Grouped paraphrase data is used only for inference/evaluation input in this notebook."
}